postmanrenderer/__init__.py
postmanrenderer/constants.py
postmanrenderer/jinja_env.py
postmanrenderer/main.py
postmanrenderer/templates/collection.j2
postmanrenderer/templates/header.j2
postmanrenderer/templates/request.j2
postmanrenderer/templates/requestBody.j2
postmanrenderer-1.0.5.dist-info/METADATA
postmanrenderer-1.0.5.dist-info/WHEEL
postmanrenderer-1.0.5.dist-info/top_level.txt
postmanrenderer-1.0.5.dist-info/RECORD
