Metadata-Version: 2.1
Name: postmanrenderer
Version: 1.0.5
Summary: Create and Export Postman collections
Home-page: UNKNOWN
Author: Aditya Nagesh
Author-email: adityagesh@gmail.com
License: MIT
Platform: UNKNOWN
Requires-Dist: Jinja2
